segmentation_sdk/__init__.py
segmentation_sdk/data_utils.py
segmentation_sdk/model_utils.py
segmentation_sdk/utils.py
segmentation_sdk/viz_utils.py
segmentation_sdk-1.0.1.dist-info/LICENSE.lic
segmentation_sdk-1.0.1.dist-info/METADATA
segmentation_sdk-1.0.1.dist-info/WHEEL
segmentation_sdk-1.0.1.dist-info/top_level.txt
segmentation_sdk-1.0.1.dist-info/RECORD
